{
	"configurations" : 
	[
		{
			"directories" : 
			[
				{
					"build" : ".",
					"jsonFile" : "directory-.-Debug-f5ebdc15457944623624.json",
					"minimumCMakeVersion" : 
					{
						"string" : "3.21"
					},
					"projectIndex" : 0,
					"source" : ".",
					"targetIndexes" : 
					[
						0
					]
				}
			],
			"name" : "Debug",
			"projects" : 
			[
				{
					"directoryIndexes" : 
					[
						0
					],
					"name" : "Echo_EPETServ",
					"targetIndexes" : 
					[
						0
					]
				}
			],
			"targets" : 
			[
				{
					"directoryIndex" : 0,
					"id" : "Echo_EPETServ::@6890427a1f51a3e7e1df",
					"jsonFile" : "target-Echo_EPETServ-Debug-6e6bb8e6f42e8af478da.json",
					"name" : "Echo_EPETServ",
					"projectIndex" : 0
				}
			]
		}
	],
	"kind" : "codemodel",
	"paths" : 
	{
		"build" : "/Users/shawnzhao/Code/Socket_Learning/Echo_EPETServ/cmake-build-debug",
		"source" : "/Users/shawnzhao/Code/Socket_Learning/Echo_EPETServ"
	},
	"version" : 
	{
		"major" : 2,
		"minor" : 3
	}
}
